gauss_binom/Binomialdistribution.py
gauss_binom/Gaussiandistribution.py
gauss_binom/Generaldistribution.py
gauss_binom/__init__.py
gauss_binom-0.1.dist-info/LICENSE
gauss_binom-0.1.dist-info/METADATA
gauss_binom-0.1.dist-info/WHEEL
gauss_binom-0.1.dist-info/top_level.txt
gauss_binom-0.1.dist-info/RECORD
