Metadata-Version: 2.1
Name: gauss-binom
Version: 0.1
Summary: Gaussian and Binomial distributions
Home-page: UNKNOWN
Author: Sudipta Chandra
Author-email: sumitac9@gmail.com
License: UNKNOWN
Platform: UNKNOWN
